sentential/__init__.py
sentential/cli/deploy.py
sentential/cli/destroy.py
sentential/cli/invoke.py
sentential/cli/logs.py
sentential/cli/mount.py
sentential/cli/policy.py
sentential/cli/root.py
sentential/cli/store.py
sentential/cli/umount.py
sentential/lib/assurances.py
sentential/lib/clients.py
sentential/lib/context.py
sentential/lib/drivers/aws_ecr.py
sentential/lib/drivers/aws_lambda.py
sentential/lib/drivers/local_bridge.py
sentential/lib/drivers/local_images.py
sentential/lib/drivers/local_lambda.py
sentential/lib/drivers/spec.py
sentential/lib/exceptions.py
sentential/lib/joinery.py
sentential/lib/mounts/aws_api_gateway.py
sentential/lib/mounts/aws_event_schedule.py
sentential/lib/mounts/aws_lambda_public_url.py
sentential/lib/mounts/local_lambda_public_url.py
sentential/lib/mounts/spec.py
sentential/lib/ontology.py
sentential/lib/shapes.py
sentential/lib/store.py
sentential/lib/template.py
sentential/sntl.py
sentential/templates/Dockerfile
sentential/templates/policy.json
sentential/templates/shapes.py
sentential-0.12.2.dist-info/LICENSE
sentential-0.12.2.dist-info/METADATA
sentential-0.12.2.dist-info/WHEEL
sentential-0.12.2.dist-info/entry_points.txt
sentential-0.12.2.dist-info/RECORD
